{
  "audience_top_25": [
    {
      "guest": "John Jumper",
      "domain": "AI biology",
      "audience_score": 95,
      "tyler_score": 94,
      "reach": 5,
      "expertise_depth": 5,
      "single_subject": 5,
      "current_relevance": 5,
      "candor": 3,
      "novelty": 5,
      "idiosyncrasy": 5,
      "prep_payoff": 5,
      "intellectual_range": 4,
      "rapport": 3,
      "audience_case": "Nobel-level breakthrough with a clean premise",
      "tyler_case": "deep scientific explanation with unusually high preparation payoff",
      "audience_top_25": true,
      "tyler_top_25": true,
      "overlap": true
    },
    {
      "guest": "A. R. Rahman",
      "domain": "music",
      "audience_score": 93,
      "tyler_score": 94,
      "reach": 4,
      "expertise_depth": 5,
      "single_subject": 5,
      "current_relevance": 5,
      "candor": 4,
      "novelty": 5,
      "idiosyncrasy": 5,
      "prep_payoff": 5,
      "intellectual_range": 4,
      "rapport": 3,
      "audience_case": "global audience and unusually broad cultural reach",
      "tyler_case": "composition, India, technology, and religious aesthetics",
      "audience_top_25": true,
      "tyler_top_25": true,
      "overlap": true
    },
    {
      "guest": "Max Martin",
      "domain": "music",
      "audience_score": 92,
      "tyler_score": 92,
      "reach": 5,
      "expertise_depth": 5,
      "single_subject": 5,
      "current_relevance": 4,
      "candor": 3,
      "novelty": 5,
      "idiosyncrasy": 5,
      "prep_payoff": 5,
      "intellectual_range": 4,
      "rapport": 3,
      "audience_case": "a universally known output with an unfamiliar maker",
      "tyler_case": "song construction, Sweden, and artistic production are classic CWT terrain",
      "audience_top_25": true,
      "tyler_top_25": true,
      "overlap": true
    },
    {
      "guest": "Kevin Esvelt",
      "domain": "biosecurity",
      "audience_score": 90,
      "tyler_score": 98,
      "reach": 3,
      "expertise_depth": 5,
      "single_subject": 5,
      "current_relevance": 5,
      "candor": 5,
      "novelty": 5,
      "idiosyncrasy": 5,
      "prep_payoff": 5,
      "intellectual_range": 5,
      "rapport": 4,
      "audience_case": "high-stakes subject with a real moral voice",
      "tyler_case": "technical depth and candid institutional criticism",
      "audience_top_25": true,
      "tyler_top_25": true,
      "overlap": true
    },
    {
      "guest": "Misha Glenny",
      "domain": "geopolitics",
      "audience_score": 90,
      "tyler_score": 98,
      "reach": 3,
      "expertise_depth": 5,
      "single_subject": 5,
      "current_relevance": 5,
      "candor": 5,
      "novelty": 5,
      "idiosyncrasy": 5,
      "prep_payoff": 5,
      "intellectual_range": 5,
      "rapport": 4,
      "audience_case": "broad relevance without pundit monotony",
      "tyler_case": "crime, technology, Central Europe, and history",
      "audience_top_25": true,
      "tyler_top_25": true,
      "overlap": true
    },
    {
      "guest": "Sarah Paine",
      "domain": "military history",
      "audience_score": 90,
      "tyler_score": 98,
      "reach": 3,
      "expertise_depth": 5,
      "single_subject": 5,
      "current_relevance": 5,
      "candor": 5,
      "novelty": 5,
      "idiosyncrasy": 5,
      "prep_payoff": 5,
      "intellectual_range": 5,
      "rapport": 4,
      "audience_case": "specialist intensity and recommendation value",
      "tyler_case": "precisely the kind of deep, surprising historical explanation Tyler prizes",
      "audience_top_25": true,
      "tyler_top_25": true,
      "overlap": true
    },
    {
      "guest": "Andrei Soldatov",
      "domain": "Russia and surveillance",
      "audience_score": 90,
      "tyler_score": 97,
      "reach": 3,
      "expertise_depth": 5,
      "single_subject": 5,
      "current_relevance": 5,
      "candor": 5,
      "novelty": 5,
      "idiosyncrasy": 5,
      "prep_payoff": 5,
      "intellectual_range": 5,
      "rapport": 3,
      "audience_case": "rare on-the-ground expertise",
      "tyler_case": "the combination of regime knowledge and direct reporting is unusually CWT-compatible",
      "audience_top_25": true,
      "tyler_top_25": true,
      "overlap": true
    },
    {
      "guest": "Kiana Hayeri",
      "domain": "photojournalism",
      "audience_score": 90,
      "tyler_score": 97,
      "reach": 3,
      "expertise_depth": 5,
      "single_subject": 5,
      "current_relevance": 5,
      "candor": 5,
      "novelty": 5,
      "idiosyncrasy": 5,
      "prep_payoff": 5,
      "intellectual_range": 5,
      "rapport": 3,
      "audience_case": "first-hand reporting gives the episode narrative momentum",
      "tyler_case": "Afghanistan, migration, aesthetics, and lived knowledge",
      "audience_top_25": true,
      "tyler_top_25": true,
      "overlap": true
    },
    {
      "guest": "Ted Chiang",
      "domain": "fiction and technology",
      "audience_score": 90,
      "tyler_score": 96,
      "reach": 4,
      "expertise_depth": 5,
      "single_subject": 5,
      "current_relevance": 4,
      "candor": 4,
      "novelty": 5,
      "idiosyncrasy": 5,
      "prep_payoff": 5,
      "intellectual_range": 5,
      "rapport": 4,
      "audience_case": "loyal, unusually discussion-prone audience",
      "tyler_case": "fiction, computation, and moral philosophy reward slow questions",
      "audience_top_25": true,
      "tyler_top_25": true,
      "overlap": true
    },
    {
      "guest": "Lisa Su",
      "domain": "semiconductors",
      "audience_score": 90,
      "tyler_score": 91,
      "reach": 5,
      "expertise_depth": 5,
      "single_subject": 4,
      "current_relevance": 5,
      "candor": 3,
      "novelty": 4,
      "idiosyncrasy": 4,
      "prep_payoff": 5,
      "intellectual_range": 4,
      "rapport": 4,
      "audience_case": "AI infrastructure with broad recognition",
      "tyler_case": "engineering, Taiwan, supply chains, and management reward preparation",
      "audience_top_25": true,
      "tyler_top_25": true,
      "overlap": true
    },
    {
      "guest": "Chris Olah",
      "domain": "AI interpretability",
      "audience_score": 88,
      "tyler_score": 97,
      "reach": 3,
      "expertise_depth": 5,
      "single_subject": 5,
      "current_relevance": 5,
      "candor": 4,
      "novelty": 5,
      "idiosyncrasy": 5,
      "prep_payoff": 5,
      "intellectual_range": 5,
      "rapport": 3,
      "audience_case": "one of the few technical AI conversations listeners would share",
      "tyler_case": "a rare chance to make a difficult frontier intelligible",
      "audience_top_25": true,
      "tyler_top_25": true,
      "overlap": true
    },
    {
      "guest": "Regina Barzilay",
      "domain": "AI medicine",
      "audience_score": 88,
      "tyler_score": 97,
      "reach": 3,
      "expertise_depth": 5,
      "single_subject": 5,
      "current_relevance": 5,
      "candor": 4,
      "novelty": 5,
      "idiosyncrasy": 5,
      "prep_payoff": 5,
      "intellectual_range": 5,
      "rapport": 3,
      "audience_case": "clear human payoff from frontier AI",
      "tyler_case": "medicine, algorithms, and personal scientific motivation",
      "audience_top_25": true,
      "tyler_top_25": true,
      "overlap": true
    },
    {
      "guest": "Patrick Radden Keefe",
      "domain": "narrative nonfiction",
      "audience_score": 88,
      "tyler_score": 96,
      "reach": 4,
      "expertise_depth": 5,
      "single_subject": 5,
      "current_relevance": 4,
      "candor": 4,
      "novelty": 4,
      "idiosyncrasy": 5,
      "prep_payoff": 5,
      "intellectual_range": 5,
      "rapport": 4,
      "audience_case": "an established long-form audience and vivid material",
      "tyler_case": "research method, state capacity, and narrative craft",
      "audience_top_25": true,
      "tyler_top_25": true,
      "overlap": true
    },
    {
      "guest": "Ngozi Okonjo-Iweala",
      "domain": "trade and development",
      "audience_score": 88,
      "tyler_score": 94,
      "reach": 4,
      "expertise_depth": 5,
      "single_subject": 4,
      "current_relevance": 5,
      "candor": 4,
      "novelty": 4,
      "idiosyncrasy": 4,
      "prep_payoff": 5,
      "intellectual_range": 5,
      "rapport": 4,
      "audience_case": "global trade with an immediately legible institutional role",
      "tyler_case": "development, Africa, trade rules, and state capacity create a high-preparation conversation",
      "audience_top_25": true,
      "tyler_top_25": true,
      "overlap": true
    },
    {
      "guest": "Tobi Lütke",
      "domain": "commerce and software",
      "audience_score": 88,
      "tyler_score": 91,
      "reach": 4,
      "expertise_depth": 5,
      "single_subject": 4,
      "current_relevance": 5,
      "candor": 4,
      "novelty": 4,
      "idiosyncrasy": 4,
      "prep_payoff": 5,
      "intellectual_range": 4,
      "rapport": 4,
      "audience_case": "credible builder with a distinct public voice",
      "tyler_case": "management, entrepreneurship, culture, and technology all travel well",
      "audience_top_25": true,
      "tyler_top_25": true,
      "overlap": true
    },
    {
      "guest": "Brian Chesky",
      "domain": "hospitality and product",
      "audience_score": 88,
      "tyler_score": 82,
      "reach": 5,
      "expertise_depth": 4,
      "single_subject": 4,
      "current_relevance": 5,
      "candor": 4,
      "novelty": 4,
      "idiosyncrasy": 4,
      "prep_payoff": 4,
      "intellectual_range": 4,
      "rapport": 4,
      "audience_case": "consumer recognition plus a real operating story",
      "tyler_case": "travel, cities, regulation, and design create many angles",
      "audience_top_25": true,
      "tyler_top_25": true,
      "overlap": true
    },
    {
      "guest": "Aidan Gomez",
      "domain": "enterprise AI",
      "audience_score": 88,
      "tyler_score": 76,
      "reach": 5,
      "expertise_depth": 4,
      "single_subject": 4,
      "current_relevance": 5,
      "candor": 4,
      "novelty": 4,
      "idiosyncrasy": 3,
      "prep_payoff": 4,
      "intellectual_range": 4,
      "rapport": 3,
      "audience_case": "founder status plus the transformer origin story",
      "tyler_case": "enterprise AI, Canada, and sovereignty open real disagreement",
      "audience_top_25": true,
      "tyler_top_25": false,
      "overlap": false
    },
    {
      "guest": "Dawn Song",
      "domain": "computer security",
      "audience_score": 86,
      "tyler_score": 97,
      "reach": 3,
      "expertise_depth": 5,
      "single_subject": 5,
      "current_relevance": 5,
      "candor": 3,
      "novelty": 5,
      "idiosyncrasy": 5,
      "prep_payoff": 5,
      "intellectual_range": 5,
      "rapport": 3,
      "audience_case": "AI and security without generic founder talk",
      "tyler_case": "technical originality and a focused subject",
      "audience_top_25": true,
      "tyler_top_25": true,
      "overlap": true
    },
    {
      "guest": "Percy Liang",
      "domain": "AI research",
      "audience_score": 86,
      "tyler_score": 97,
      "reach": 3,
      "expertise_depth": 5,
      "single_subject": 5,
      "current_relevance": 5,
      "candor": 4,
      "novelty": 4,
      "idiosyncrasy": 5,
      "prep_payoff": 5,
      "intellectual_range": 5,
      "rapport": 3,
      "audience_case": "a credible, less overexposed AI expert",
      "tyler_case": "excellent fit for questions on evaluation and the production function of science",
      "audience_top_25": true,
      "tyler_top_25": true,
      "overlap": true
    },
    {
      "guest": "Caitlin Talmadge",
      "domain": "security studies",
      "audience_score": 86,
      "tyler_score": 94,
      "reach": 3,
      "expertise_depth": 5,
      "single_subject": 5,
      "current_relevance": 5,
      "candor": 4,
      "novelty": 4,
      "idiosyncrasy": 4,
      "prep_payoff": 5,
      "intellectual_range": 5,
      "rapport": 4,
      "audience_case": "war and deterrence have immediate relevance",
      "tyler_case": "technical strategy plus an accessible explanatory style",
      "audience_top_25": true,
      "tyler_top_25": true,
      "overlap": true
    },
    {
      "guest": "Mustafa Suleyman",
      "domain": "AI policy",
      "audience_score": 86,
      "tyler_score": 76,
      "reach": 5,
      "expertise_depth": 4,
      "single_subject": 4,
      "current_relevance": 5,
      "candor": 4,
      "novelty": 3,
      "idiosyncrasy": 3,
      "prep_payoff": 4,
      "intellectual_range": 4,
      "rapport": 3,
      "audience_case": "large current AI audience and clear stakes",
      "tyler_case": "good policy and organizational tension, less distinctive than technical peers",
      "audience_top_25": true,
      "tyler_top_25": false,
      "overlap": false
    },
    {
      "guest": "Hernan Diaz",
      "domain": "fiction",
      "audience_score": 85,
      "tyler_score": 96,
      "reach": 3,
      "expertise_depth": 5,
      "single_subject": 5,
      "current_relevance": 4,
      "candor": 4,
      "novelty": 5,
      "idiosyncrasy": 5,
      "prep_payoff": 5,
      "intellectual_range": 5,
      "rapport": 4,
      "audience_case": "a distinctive author likely to generate strong word of mouth",
      "tyler_case": "literature, capitalism, and form create unusually rich preparation payoff",
      "audience_top_25": true,
      "tyler_top_25": true,
      "overlap": true
    },
    {
      "guest": "Michael Levin",
      "domain": "developmental biology",
      "audience_score": 85,
      "tyler_score": 96,
      "reach": 3,
      "expertise_depth": 5,
      "single_subject": 5,
      "current_relevance": 4,
      "candor": 4,
      "novelty": 5,
      "idiosyncrasy": 5,
      "prep_payoff": 5,
      "intellectual_range": 5,
      "rapport": 4,
      "audience_case": "high recommendation value for curious listeners",
      "tyler_case": "the strongest pure Tyler-fit: unusual theory, experiment, and vocabulary",
      "audience_top_25": true,
      "tyler_top_25": true,
      "overlap": true
    },
    {
      "guest": "Kori Schake",
      "domain": "security studies",
      "audience_score": 85,
      "tyler_score": 94,
      "reach": 3,
      "expertise_depth": 5,
      "single_subject": 4,
      "current_relevance": 5,
      "candor": 5,
      "novelty": 4,
      "idiosyncrasy": 4,
      "prep_payoff": 5,
      "intellectual_range": 5,
      "rapport": 4,
      "audience_case": "clear and timely foreign-policy conversation",
      "tyler_case": "institutional experience, history, and frank strategic judgment",
      "audience_top_25": true,
      "tyler_top_25": true,
      "overlap": true
    },
    {
      "guest": "Mira Murati",
      "domain": "AI leadership",
      "audience_score": 84,
      "tyler_score": 70,
      "reach": 5,
      "expertise_depth": 3,
      "single_subject": 4,
      "current_relevance": 5,
      "candor": 4,
      "novelty": 4,
      "idiosyncrasy": 3,
      "prep_payoff": 4,
      "intellectual_range": 4,
      "rapport": 3,
      "audience_case": "rare access to a central AI actor",
      "tyler_case": "useful institutional and technical transition story",
      "audience_top_25": true,
      "tyler_top_25": false,
      "overlap": false
    }
  ],
  "tyler_top_25": [
    {
      "guest": "Kevin Esvelt",
      "domain": "biosecurity",
      "audience_score": 90,
      "tyler_score": 98,
      "reach": 3,
      "expertise_depth": 5,
      "single_subject": 5,
      "current_relevance": 5,
      "candor": 5,
      "novelty": 5,
      "idiosyncrasy": 5,
      "prep_payoff": 5,
      "intellectual_range": 5,
      "rapport": 4,
      "audience_case": "high-stakes subject with a real moral voice",
      "tyler_case": "technical depth and candid institutional criticism",
      "audience_top_25": true,
      "tyler_top_25": true,
      "overlap": true
    },
    {
      "guest": "Misha Glenny",
      "domain": "geopolitics",
      "audience_score": 90,
      "tyler_score": 98,
      "reach": 3,
      "expertise_depth": 5,
      "single_subject": 5,
      "current_relevance": 5,
      "candor": 5,
      "novelty": 5,
      "idiosyncrasy": 5,
      "prep_payoff": 5,
      "intellectual_range": 5,
      "rapport": 4,
      "audience_case": "broad relevance without pundit monotony",
      "tyler_case": "crime, technology, Central Europe, and history",
      "audience_top_25": true,
      "tyler_top_25": true,
      "overlap": true
    },
    {
      "guest": "Sarah Paine",
      "domain": "military history",
      "audience_score": 90,
      "tyler_score": 98,
      "reach": 3,
      "expertise_depth": 5,
      "single_subject": 5,
      "current_relevance": 5,
      "candor": 5,
      "novelty": 5,
      "idiosyncrasy": 5,
      "prep_payoff": 5,
      "intellectual_range": 5,
      "rapport": 4,
      "audience_case": "specialist intensity and recommendation value",
      "tyler_case": "precisely the kind of deep, surprising historical explanation Tyler prizes",
      "audience_top_25": true,
      "tyler_top_25": true,
      "overlap": true
    },
    {
      "guest": "Andrei Soldatov",
      "domain": "Russia and surveillance",
      "audience_score": 90,
      "tyler_score": 97,
      "reach": 3,
      "expertise_depth": 5,
      "single_subject": 5,
      "current_relevance": 5,
      "candor": 5,
      "novelty": 5,
      "idiosyncrasy": 5,
      "prep_payoff": 5,
      "intellectual_range": 5,
      "rapport": 3,
      "audience_case": "rare on-the-ground expertise",
      "tyler_case": "the combination of regime knowledge and direct reporting is unusually CWT-compatible",
      "audience_top_25": true,
      "tyler_top_25": true,
      "overlap": true
    },
    {
      "guest": "Kiana Hayeri",
      "domain": "photojournalism",
      "audience_score": 90,
      "tyler_score": 97,
      "reach": 3,
      "expertise_depth": 5,
      "single_subject": 5,
      "current_relevance": 5,
      "candor": 5,
      "novelty": 5,
      "idiosyncrasy": 5,
      "prep_payoff": 5,
      "intellectual_range": 5,
      "rapport": 3,
      "audience_case": "first-hand reporting gives the episode narrative momentum",
      "tyler_case": "Afghanistan, migration, aesthetics, and lived knowledge",
      "audience_top_25": true,
      "tyler_top_25": true,
      "overlap": true
    },
    {
      "guest": "Chris Olah",
      "domain": "AI interpretability",
      "audience_score": 88,
      "tyler_score": 97,
      "reach": 3,
      "expertise_depth": 5,
      "single_subject": 5,
      "current_relevance": 5,
      "candor": 4,
      "novelty": 5,
      "idiosyncrasy": 5,
      "prep_payoff": 5,
      "intellectual_range": 5,
      "rapport": 3,
      "audience_case": "one of the few technical AI conversations listeners would share",
      "tyler_case": "a rare chance to make a difficult frontier intelligible",
      "audience_top_25": true,
      "tyler_top_25": true,
      "overlap": true
    },
    {
      "guest": "Regina Barzilay",
      "domain": "AI medicine",
      "audience_score": 88,
      "tyler_score": 97,
      "reach": 3,
      "expertise_depth": 5,
      "single_subject": 5,
      "current_relevance": 5,
      "candor": 4,
      "novelty": 5,
      "idiosyncrasy": 5,
      "prep_payoff": 5,
      "intellectual_range": 5,
      "rapport": 3,
      "audience_case": "clear human payoff from frontier AI",
      "tyler_case": "medicine, algorithms, and personal scientific motivation",
      "audience_top_25": true,
      "tyler_top_25": true,
      "overlap": true
    },
    {
      "guest": "Dawn Song",
      "domain": "computer security",
      "audience_score": 86,
      "tyler_score": 97,
      "reach": 3,
      "expertise_depth": 5,
      "single_subject": 5,
      "current_relevance": 5,
      "candor": 3,
      "novelty": 5,
      "idiosyncrasy": 5,
      "prep_payoff": 5,
      "intellectual_range": 5,
      "rapport": 3,
      "audience_case": "AI and security without generic founder talk",
      "tyler_case": "technical originality and a focused subject",
      "audience_top_25": true,
      "tyler_top_25": true,
      "overlap": true
    },
    {
      "guest": "Percy Liang",
      "domain": "AI research",
      "audience_score": 86,
      "tyler_score": 97,
      "reach": 3,
      "expertise_depth": 5,
      "single_subject": 5,
      "current_relevance": 5,
      "candor": 4,
      "novelty": 4,
      "idiosyncrasy": 5,
      "prep_payoff": 5,
      "intellectual_range": 5,
      "rapport": 3,
      "audience_case": "a credible, less overexposed AI expert",
      "tyler_case": "excellent fit for questions on evaluation and the production function of science",
      "audience_top_25": true,
      "tyler_top_25": true,
      "overlap": true
    },
    {
      "guest": "Ted Chiang",
      "domain": "fiction and technology",
      "audience_score": 90,
      "tyler_score": 96,
      "reach": 4,
      "expertise_depth": 5,
      "single_subject": 5,
      "current_relevance": 4,
      "candor": 4,
      "novelty": 5,
      "idiosyncrasy": 5,
      "prep_payoff": 5,
      "intellectual_range": 5,
      "rapport": 4,
      "audience_case": "loyal, unusually discussion-prone audience",
      "tyler_case": "fiction, computation, and moral philosophy reward slow questions",
      "audience_top_25": true,
      "tyler_top_25": true,
      "overlap": true
    },
    {
      "guest": "Patrick Radden Keefe",
      "domain": "narrative nonfiction",
      "audience_score": 88,
      "tyler_score": 96,
      "reach": 4,
      "expertise_depth": 5,
      "single_subject": 5,
      "current_relevance": 4,
      "candor": 4,
      "novelty": 4,
      "idiosyncrasy": 5,
      "prep_payoff": 5,
      "intellectual_range": 5,
      "rapport": 4,
      "audience_case": "an established long-form audience and vivid material",
      "tyler_case": "research method, state capacity, and narrative craft",
      "audience_top_25": true,
      "tyler_top_25": true,
      "overlap": true
    },
    {
      "guest": "Hernan Diaz",
      "domain": "fiction",
      "audience_score": 85,
      "tyler_score": 96,
      "reach": 3,
      "expertise_depth": 5,
      "single_subject": 5,
      "current_relevance": 4,
      "candor": 4,
      "novelty": 5,
      "idiosyncrasy": 5,
      "prep_payoff": 5,
      "intellectual_range": 5,
      "rapport": 4,
      "audience_case": "a distinctive author likely to generate strong word of mouth",
      "tyler_case": "literature, capitalism, and form create unusually rich preparation payoff",
      "audience_top_25": true,
      "tyler_top_25": true,
      "overlap": true
    },
    {
      "guest": "Michael Levin",
      "domain": "developmental biology",
      "audience_score": 85,
      "tyler_score": 96,
      "reach": 3,
      "expertise_depth": 5,
      "single_subject": 5,
      "current_relevance": 4,
      "candor": 4,
      "novelty": 5,
      "idiosyncrasy": 5,
      "prep_payoff": 5,
      "intellectual_range": 5,
      "rapport": 4,
      "audience_case": "high recommendation value for curious listeners",
      "tyler_case": "the strongest pure Tyler-fit: unusual theory, experiment, and vocabulary",
      "audience_top_25": true,
      "tyler_top_25": true,
      "overlap": true
    },
    {
      "guest": "Amor Towles",
      "domain": "fiction",
      "audience_score": 83,
      "tyler_score": 96,
      "reach": 3,
      "expertise_depth": 5,
      "single_subject": 5,
      "current_relevance": 4,
      "candor": 4,
      "novelty": 4,
      "idiosyncrasy": 5,
      "prep_payoff": 5,
      "intellectual_range": 5,
      "rapport": 4,
      "audience_case": "large book audience and accessible conversational style",
      "tyler_case": "historical imagination, Russia, and social observation",
      "audience_top_25": false,
      "tyler_top_25": true,
      "overlap": false
    },
    {
      "guest": "Venki Ramakrishnan",
      "domain": "biology",
      "audience_score": 83,
      "tyler_score": 96,
      "reach": 3,
      "expertise_depth": 5,
      "single_subject": 5,
      "current_relevance": 4,
      "candor": 4,
      "novelty": 4,
      "idiosyncrasy": 5,
      "prep_payoff": 5,
      "intellectual_range": 5,
      "rapport": 4,
      "audience_case": "Nobel prestige with a tractable human story",
      "tyler_case": "science, institutions, India, and autobiography",
      "audience_top_25": false,
      "tyler_top_25": true,
      "overlap": false
    },
    {
      "guest": "Katherine De Kleer",
      "domain": "planetary science",
      "audience_score": 78,
      "tyler_score": 95,
      "reach": 2,
      "expertise_depth": 5,
      "single_subject": 5,
      "current_relevance": 4,
      "candor": 3,
      "novelty": 5,
      "idiosyncrasy": 5,
      "prep_payoff": 5,
      "intellectual_range": 5,
      "rapport": 3,
      "audience_case": "a compelling niche-science surprise",
      "tyler_case": "pure expertise and an alien world, with a clear single subject",
      "audience_top_25": false,
      "tyler_top_25": true,
      "overlap": false
    },
    {
      "guest": "John Jumper",
      "domain": "AI biology",
      "audience_score": 95,
      "tyler_score": 94,
      "reach": 5,
      "expertise_depth": 5,
      "single_subject": 5,
      "current_relevance": 5,
      "candor": 3,
      "novelty": 5,
      "idiosyncrasy": 5,
      "prep_payoff": 5,
      "intellectual_range": 4,
      "rapport": 3,
      "audience_case": "Nobel-level breakthrough with a clean premise",
      "tyler_case": "deep scientific explanation with unusually high preparation payoff",
      "audience_top_25": true,
      "tyler_top_25": true,
      "overlap": true
    },
    {
      "guest": "A. R. Rahman",
      "domain": "music",
      "audience_score": 93,
      "tyler_score": 94,
      "reach": 4,
      "expertise_depth": 5,
      "single_subject": 5,
      "current_relevance": 5,
      "candor": 4,
      "novelty": 5,
      "idiosyncrasy": 5,
      "prep_payoff": 5,
      "intellectual_range": 4,
      "rapport": 3,
      "audience_case": "global audience and unusually broad cultural reach",
      "tyler_case": "composition, India, technology, and religious aesthetics",
      "audience_top_25": true,
      "tyler_top_25": true,
      "overlap": true
    },
    {
      "guest": "Ngozi Okonjo-Iweala",
      "domain": "trade and development",
      "audience_score": 88,
      "tyler_score": 94,
      "reach": 4,
      "expertise_depth": 5,
      "single_subject": 4,
      "current_relevance": 5,
      "candor": 4,
      "novelty": 4,
      "idiosyncrasy": 4,
      "prep_payoff": 5,
      "intellectual_range": 5,
      "rapport": 4,
      "audience_case": "global trade with an immediately legible institutional role",
      "tyler_case": "development, Africa, trade rules, and state capacity create a high-preparation conversation",
      "audience_top_25": true,
      "tyler_top_25": true,
      "overlap": true
    },
    {
      "guest": "Caitlin Talmadge",
      "domain": "security studies",
      "audience_score": 86,
      "tyler_score": 94,
      "reach": 3,
      "expertise_depth": 5,
      "single_subject": 5,
      "current_relevance": 5,
      "candor": 4,
      "novelty": 4,
      "idiosyncrasy": 4,
      "prep_payoff": 5,
      "intellectual_range": 5,
      "rapport": 4,
      "audience_case": "war and deterrence have immediate relevance",
      "tyler_case": "technical strategy plus an accessible explanatory style",
      "audience_top_25": true,
      "tyler_top_25": true,
      "overlap": true
    },
    {
      "guest": "Kori Schake",
      "domain": "security studies",
      "audience_score": 85,
      "tyler_score": 94,
      "reach": 3,
      "expertise_depth": 5,
      "single_subject": 4,
      "current_relevance": 5,
      "candor": 5,
      "novelty": 4,
      "idiosyncrasy": 4,
      "prep_payoff": 5,
      "intellectual_range": 5,
      "rapport": 4,
      "audience_case": "clear and timely foreign-policy conversation",
      "tyler_case": "institutional experience, history, and frank strategic judgment",
      "audience_top_25": true,
      "tyler_top_25": true,
      "overlap": true
    },
    {
      "guest": "Max Martin",
      "domain": "music",
      "audience_score": 92,
      "tyler_score": 92,
      "reach": 5,
      "expertise_depth": 5,
      "single_subject": 5,
      "current_relevance": 4,
      "candor": 3,
      "novelty": 5,
      "idiosyncrasy": 5,
      "prep_payoff": 5,
      "intellectual_range": 4,
      "rapport": 3,
      "audience_case": "a universally known output with an unfamiliar maker",
      "tyler_case": "song construction, Sweden, and artistic production are classic CWT terrain",
      "audience_top_25": true,
      "tyler_top_25": true,
      "overlap": true
    },
    {
      "guest": "Lisa Su",
      "domain": "semiconductors",
      "audience_score": 90,
      "tyler_score": 91,
      "reach": 5,
      "expertise_depth": 5,
      "single_subject": 4,
      "current_relevance": 5,
      "candor": 3,
      "novelty": 4,
      "idiosyncrasy": 4,
      "prep_payoff": 5,
      "intellectual_range": 4,
      "rapport": 4,
      "audience_case": "AI infrastructure with broad recognition",
      "tyler_case": "engineering, Taiwan, supply chains, and management reward preparation",
      "audience_top_25": true,
      "tyler_top_25": true,
      "overlap": true
    },
    {
      "guest": "Tobi Lütke",
      "domain": "commerce and software",
      "audience_score": 88,
      "tyler_score": 91,
      "reach": 4,
      "expertise_depth": 5,
      "single_subject": 4,
      "current_relevance": 5,
      "candor": 4,
      "novelty": 4,
      "idiosyncrasy": 4,
      "prep_payoff": 5,
      "intellectual_range": 4,
      "rapport": 4,
      "audience_case": "credible builder with a distinct public voice",
      "tyler_case": "management, entrepreneurship, culture, and technology all travel well",
      "audience_top_25": true,
      "tyler_top_25": true,
      "overlap": true
    },
    {
      "guest": "Brian Chesky",
      "domain": "hospitality and product",
      "audience_score": 88,
      "tyler_score": 82,
      "reach": 5,
      "expertise_depth": 4,
      "single_subject": 4,
      "current_relevance": 5,
      "candor": 4,
      "novelty": 4,
      "idiosyncrasy": 4,
      "prep_payoff": 4,
      "intellectual_range": 4,
      "rapport": 4,
      "audience_case": "consumer recognition plus a real operating story",
      "tyler_case": "travel, cities, regulation, and design create many angles",
      "audience_top_25": true,
      "tyler_top_25": true,
      "overlap": true
    }
  ],
  "overlap": [
    {
      "guest": "Lisa Su",
      "domain": "semiconductors",
      "audience_score": 90,
      "tyler_score": 91,
      "reach": 5,
      "expertise_depth": 5,
      "single_subject": 4,
      "current_relevance": 5,
      "candor": 3,
      "novelty": 4,
      "idiosyncrasy": 4,
      "prep_payoff": 5,
      "intellectual_range": 4,
      "rapport": 4,
      "audience_case": "AI infrastructure with broad recognition",
      "tyler_case": "engineering, Taiwan, supply chains, and management reward preparation",
      "audience_top_25": true,
      "tyler_top_25": true,
      "overlap": true
    },
    {
      "guest": "Brian Chesky",
      "domain": "hospitality and product",
      "audience_score": 88,
      "tyler_score": 82,
      "reach": 5,
      "expertise_depth": 4,
      "single_subject": 4,
      "current_relevance": 5,
      "candor": 4,
      "novelty": 4,
      "idiosyncrasy": 4,
      "prep_payoff": 4,
      "intellectual_range": 4,
      "rapport": 4,
      "audience_case": "consumer recognition plus a real operating story",
      "tyler_case": "travel, cities, regulation, and design create many angles",
      "audience_top_25": true,
      "tyler_top_25": true,
      "overlap": true
    },
    {
      "guest": "John Jumper",
      "domain": "AI biology",
      "audience_score": 95,
      "tyler_score": 94,
      "reach": 5,
      "expertise_depth": 5,
      "single_subject": 5,
      "current_relevance": 5,
      "candor": 3,
      "novelty": 5,
      "idiosyncrasy": 5,
      "prep_payoff": 5,
      "intellectual_range": 4,
      "rapport": 3,
      "audience_case": "Nobel-level breakthrough with a clean premise",
      "tyler_case": "deep scientific explanation with unusually high preparation payoff",
      "audience_top_25": true,
      "tyler_top_25": true,
      "overlap": true
    },
    {
      "guest": "Tobi Lütke",
      "domain": "commerce and software",
      "audience_score": 88,
      "tyler_score": 91,
      "reach": 4,
      "expertise_depth": 5,
      "single_subject": 4,
      "current_relevance": 5,
      "candor": 4,
      "novelty": 4,
      "idiosyncrasy": 4,
      "prep_payoff": 5,
      "intellectual_range": 4,
      "rapport": 4,
      "audience_case": "credible builder with a distinct public voice",
      "tyler_case": "management, entrepreneurship, culture, and technology all travel well",
      "audience_top_25": true,
      "tyler_top_25": true,
      "overlap": true
    },
    {
      "guest": "Max Martin",
      "domain": "music",
      "audience_score": 92,
      "tyler_score": 92,
      "reach": 5,
      "expertise_depth": 5,
      "single_subject": 5,
      "current_relevance": 4,
      "candor": 3,
      "novelty": 5,
      "idiosyncrasy": 5,
      "prep_payoff": 5,
      "intellectual_range": 4,
      "rapport": 3,
      "audience_case": "a universally known output with an unfamiliar maker",
      "tyler_case": "song construction, Sweden, and artistic production are classic CWT terrain",
      "audience_top_25": true,
      "tyler_top_25": true,
      "overlap": true
    },
    {
      "guest": "Michael Levin",
      "domain": "developmental biology",
      "audience_score": 85,
      "tyler_score": 96,
      "reach": 3,
      "expertise_depth": 5,
      "single_subject": 5,
      "current_relevance": 4,
      "candor": 4,
      "novelty": 5,
      "idiosyncrasy": 5,
      "prep_payoff": 5,
      "intellectual_range": 5,
      "rapport": 4,
      "audience_case": "high recommendation value for curious listeners",
      "tyler_case": "the strongest pure Tyler-fit: unusual theory, experiment, and vocabulary",
      "audience_top_25": true,
      "tyler_top_25": true,
      "overlap": true
    },
    {
      "guest": "Kevin Esvelt",
      "domain": "biosecurity",
      "audience_score": 90,
      "tyler_score": 98,
      "reach": 3,
      "expertise_depth": 5,
      "single_subject": 5,
      "current_relevance": 5,
      "candor": 5,
      "novelty": 5,
      "idiosyncrasy": 5,
      "prep_payoff": 5,
      "intellectual_range": 5,
      "rapport": 4,
      "audience_case": "high-stakes subject with a real moral voice",
      "tyler_case": "technical depth and candid institutional criticism",
      "audience_top_25": true,
      "tyler_top_25": true,
      "overlap": true
    },
    {
      "guest": "Ted Chiang",
      "domain": "fiction and technology",
      "audience_score": 90,
      "tyler_score": 96,
      "reach": 4,
      "expertise_depth": 5,
      "single_subject": 5,
      "current_relevance": 4,
      "candor": 4,
      "novelty": 5,
      "idiosyncrasy": 5,
      "prep_payoff": 5,
      "intellectual_range": 5,
      "rapport": 4,
      "audience_case": "loyal, unusually discussion-prone audience",
      "tyler_case": "fiction, computation, and moral philosophy reward slow questions",
      "audience_top_25": true,
      "tyler_top_25": true,
      "overlap": true
    },
    {
      "guest": "Chris Olah",
      "domain": "AI interpretability",
      "audience_score": 88,
      "tyler_score": 97,
      "reach": 3,
      "expertise_depth": 5,
      "single_subject": 5,
      "current_relevance": 5,
      "candor": 4,
      "novelty": 5,
      "idiosyncrasy": 5,
      "prep_payoff": 5,
      "intellectual_range": 5,
      "rapport": 3,
      "audience_case": "one of the few technical AI conversations listeners would share",
      "tyler_case": "a rare chance to make a difficult frontier intelligible",
      "audience_top_25": true,
      "tyler_top_25": true,
      "overlap": true
    },
    {
      "guest": "Patrick Radden Keefe",
      "domain": "narrative nonfiction",
      "audience_score": 88,
      "tyler_score": 96,
      "reach": 4,
      "expertise_depth": 5,
      "single_subject": 5,
      "current_relevance": 4,
      "candor": 4,
      "novelty": 4,
      "idiosyncrasy": 5,
      "prep_payoff": 5,
      "intellectual_range": 5,
      "rapport": 4,
      "audience_case": "an established long-form audience and vivid material",
      "tyler_case": "research method, state capacity, and narrative craft",
      "audience_top_25": true,
      "tyler_top_25": true,
      "overlap": true
    },
    {
      "guest": "A. R. Rahman",
      "domain": "music",
      "audience_score": 93,
      "tyler_score": 94,
      "reach": 4,
      "expertise_depth": 5,
      "single_subject": 5,
      "current_relevance": 5,
      "candor": 4,
      "novelty": 5,
      "idiosyncrasy": 5,
      "prep_payoff": 5,
      "intellectual_range": 4,
      "rapport": 3,
      "audience_case": "global audience and unusually broad cultural reach",
      "tyler_case": "composition, India, technology, and religious aesthetics",
      "audience_top_25": true,
      "tyler_top_25": true,
      "overlap": true
    },
    {
      "guest": "Ngozi Okonjo-Iweala",
      "domain": "trade and development",
      "audience_score": 88,
      "tyler_score": 94,
      "reach": 4,
      "expertise_depth": 5,
      "single_subject": 4,
      "current_relevance": 5,
      "candor": 4,
      "novelty": 4,
      "idiosyncrasy": 4,
      "prep_payoff": 5,
      "intellectual_range": 5,
      "rapport": 4,
      "audience_case": "global trade with an immediately legible institutional role",
      "tyler_case": "development, Africa, trade rules, and state capacity create a high-preparation conversation",
      "audience_top_25": true,
      "tyler_top_25": true,
      "overlap": true
    },
    {
      "guest": "Sarah Paine",
      "domain": "military history",
      "audience_score": 90,
      "tyler_score": 98,
      "reach": 3,
      "expertise_depth": 5,
      "single_subject": 5,
      "current_relevance": 5,
      "candor": 5,
      "novelty": 5,
      "idiosyncrasy": 5,
      "prep_payoff": 5,
      "intellectual_range": 5,
      "rapport": 4,
      "audience_case": "specialist intensity and recommendation value",
      "tyler_case": "precisely the kind of deep, surprising historical explanation Tyler prizes",
      "audience_top_25": true,
      "tyler_top_25": true,
      "overlap": true
    },
    {
      "guest": "Caitlin Talmadge",
      "domain": "security studies",
      "audience_score": 86,
      "tyler_score": 94,
      "reach": 3,
      "expertise_depth": 5,
      "single_subject": 5,
      "current_relevance": 5,
      "candor": 4,
      "novelty": 4,
      "idiosyncrasy": 4,
      "prep_payoff": 5,
      "intellectual_range": 5,
      "rapport": 4,
      "audience_case": "war and deterrence have immediate relevance",
      "tyler_case": "technical strategy plus an accessible explanatory style",
      "audience_top_25": true,
      "tyler_top_25": true,
      "overlap": true
    },
    {
      "guest": "Andrei Soldatov",
      "domain": "Russia and surveillance",
      "audience_score": 90,
      "tyler_score": 97,
      "reach": 3,
      "expertise_depth": 5,
      "single_subject": 5,
      "current_relevance": 5,
      "candor": 5,
      "novelty": 5,
      "idiosyncrasy": 5,
      "prep_payoff": 5,
      "intellectual_range": 5,
      "rapport": 3,
      "audience_case": "rare on-the-ground expertise",
      "tyler_case": "the combination of regime knowledge and direct reporting is unusually CWT-compatible",
      "audience_top_25": true,
      "tyler_top_25": true,
      "overlap": true
    },
    {
      "guest": "Kori Schake",
      "domain": "security studies",
      "audience_score": 85,
      "tyler_score": 94,
      "reach": 3,
      "expertise_depth": 5,
      "single_subject": 4,
      "current_relevance": 5,
      "candor": 5,
      "novelty": 4,
      "idiosyncrasy": 4,
      "prep_payoff": 5,
      "intellectual_range": 5,
      "rapport": 4,
      "audience_case": "clear and timely foreign-policy conversation",
      "tyler_case": "institutional experience, history, and frank strategic judgment",
      "audience_top_25": true,
      "tyler_top_25": true,
      "overlap": true
    },
    {
      "guest": "Dawn Song",
      "domain": "computer security",
      "audience_score": 86,
      "tyler_score": 97,
      "reach": 3,
      "expertise_depth": 5,
      "single_subject": 5,
      "current_relevance": 5,
      "candor": 3,
      "novelty": 5,
      "idiosyncrasy": 5,
      "prep_payoff": 5,
      "intellectual_range": 5,
      "rapport": 3,
      "audience_case": "AI and security without generic founder talk",
      "tyler_case": "technical originality and a focused subject",
      "audience_top_25": true,
      "tyler_top_25": true,
      "overlap": true
    },
    {
      "guest": "Regina Barzilay",
      "domain": "AI medicine",
      "audience_score": 88,
      "tyler_score": 97,
      "reach": 3,
      "expertise_depth": 5,
      "single_subject": 5,
      "current_relevance": 5,
      "candor": 4,
      "novelty": 5,
      "idiosyncrasy": 5,
      "prep_payoff": 5,
      "intellectual_range": 5,
      "rapport": 3,
      "audience_case": "clear human payoff from frontier AI",
      "tyler_case": "medicine, algorithms, and personal scientific motivation",
      "audience_top_25": true,
      "tyler_top_25": true,
      "overlap": true
    },
    {
      "guest": "Percy Liang",
      "domain": "AI research",
      "audience_score": 86,
      "tyler_score": 97,
      "reach": 3,
      "expertise_depth": 5,
      "single_subject": 5,
      "current_relevance": 5,
      "candor": 4,
      "novelty": 4,
      "idiosyncrasy": 5,
      "prep_payoff": 5,
      "intellectual_range": 5,
      "rapport": 3,
      "audience_case": "a credible, less overexposed AI expert",
      "tyler_case": "excellent fit for questions on evaluation and the production function of science",
      "audience_top_25": true,
      "tyler_top_25": true,
      "overlap": true
    },
    {
      "guest": "Hernan Diaz",
      "domain": "fiction",
      "audience_score": 85,
      "tyler_score": 96,
      "reach": 3,
      "expertise_depth": 5,
      "single_subject": 5,
      "current_relevance": 4,
      "candor": 4,
      "novelty": 5,
      "idiosyncrasy": 5,
      "prep_payoff": 5,
      "intellectual_range": 5,
      "rapport": 4,
      "audience_case": "a distinctive author likely to generate strong word of mouth",
      "tyler_case": "literature, capitalism, and form create unusually rich preparation payoff",
      "audience_top_25": true,
      "tyler_top_25": true,
      "overlap": true
    },
    {
      "guest": "Kiana Hayeri",
      "domain": "photojournalism",
      "audience_score": 90,
      "tyler_score": 97,
      "reach": 3,
      "expertise_depth": 5,
      "single_subject": 5,
      "current_relevance": 5,
      "candor": 5,
      "novelty": 5,
      "idiosyncrasy": 5,
      "prep_payoff": 5,
      "intellectual_range": 5,
      "rapport": 3,
      "audience_case": "first-hand reporting gives the episode narrative momentum",
      "tyler_case": "Afghanistan, migration, aesthetics, and lived knowledge",
      "audience_top_25": true,
      "tyler_top_25": true,
      "overlap": true
    },
    {
      "guest": "Misha Glenny",
      "domain": "geopolitics",
      "audience_score": 90,
      "tyler_score": 98,
      "reach": 3,
      "expertise_depth": 5,
      "single_subject": 5,
      "current_relevance": 5,
      "candor": 5,
      "novelty": 5,
      "idiosyncrasy": 5,
      "prep_payoff": 5,
      "intellectual_range": 5,
      "rapport": 4,
      "audience_case": "broad relevance without pundit monotony",
      "tyler_case": "crime, technology, Central Europe, and history",
      "audience_top_25": true,
      "tyler_top_25": true,
      "overlap": true
    }
  ],
  "formula": {
    "audience": "20*(.24*reach + .22*expertise + .18*specificity + .16*current + .12*candor + .08*novelty)",
    "tyler": "20*(.29*expertise + .22*idiosyncrasy + .18*prep payoff + .13*range + .10*current + .08*rapport)"
  }
}